apikee/__init__.py
apikee/exceptions.py
apikee/middleware.py
apikee/settings.py
apikee-1.0.6.dist-info/METADATA
apikee-1.0.6.dist-info/WHEEL
apikee-1.0.6.dist-info/top_level.txt
apikee-1.0.6.dist-info/RECORD
