Metadata-Version: 2.1
Name: apikee
Version: 1.0.6
Summary: ApiKee - A lightweight API key validation library for FastAPI
Home-page: https://github.com/apikee-dev/apikee-python
Author: usmhic
License: MIT
Requires-Python: >=3.7
Requires-Dist: aiohttp>=3.8.0
